drcodecover/__init__.py
drcodecover/drcodecover.py
drcodecover-1.0.3.dist-info/METADATA
drcodecover-1.0.3.dist-info/WHEEL
drcodecover-1.0.3.dist-info/top_level.txt
drcodecover-1.0.3.dist-info/RECORD
