Metadata-Version: 2.1
Name: drcodecover
Version: 1.0.3
Summary: A special package for Sentry integration with advanced configuration options.
Home-page: https://github.com/codewithnadeem14502/drcode-wrapper-python
Author: Mohd Nadeem
Author-email: codewithnadeem@gmail.com
Project-URL: Documentation, https://github.com/codewithnadeem14502/drcode-wrapper-python#readme
Project-URL: Source, https://github.com/codewithnadeem14502/drcode-wrapper-python
Classifier: Programming Language :: Python :: 3
Classifier: License :: OSI Approved :: MIT License
Classifier: Operating System :: OS Independent
Classifier: Intended Audience :: Developers
Classifier: Topic :: Software Development :: Libraries :: Python Modules
Requires-Python: >=3.6
Requires-Dist: sentry-sdk >=2.0.0
